micromagneticdata/__init__.py
micromagneticdata/abstract_drive.py
micromagneticdata/combined_drive.py
micromagneticdata/data.py
micromagneticdata/drive.py
micromagneticdata/mumax3drive.py
micromagneticdata/oommfdrive.py
micromagneticdata/tests/__init__.py
micromagneticdata/tests/generate_test_data.py
micromagneticdata/tests/test_combined_drive.py
micromagneticdata/tests/test_data.py
micromagneticdata/tests/test_drive.py
micromagneticdata/tests/test_sample/hysteresis/drive-0/hysteresis-Oxs_MinDriver-Magnetization-00-0000018.omf
micromagneticdata/tests/test_sample/hysteresis/drive-0/hysteresis-Oxs_MinDriver-Magnetization-01-0000032.omf
micromagneticdata/tests/test_sample/hysteresis/drive-0/hysteresis-Oxs_MinDriver-Magnetization-02-0000047.omf
micromagneticdata/tests/test_sample/hysteresis/drive-0/hysteresis-Oxs_MinDriver-Magnetization-03-0000062.omf
micromagneticdata/tests/test_sample/hysteresis/drive-0/hysteresis-Oxs_MinDriver-Magnetization-04-0000078.omf
micromagneticdata/tests/test_sample/hysteresis/drive-0/hysteresis-Oxs_MinDriver-Magnetization-05-0000094.omf
micromagneticdata/tests/test_sample/hysteresis/drive-0/hysteresis-Oxs_MinDriver-Magnetization-06-0000111.omf
micromagneticdata/tests/test_sample/hysteresis/drive-0/hysteresis-Oxs_MinDriver-Magnetization-07-0000129.omf
micromagneticdata/tests/test_sample/hysteresis/drive-0/hysteresis-Oxs_MinDriver-Magnetization-08-0000148.omf
micromagneticdata/tests/test_sample/hysteresis/drive-0/hysteresis-Oxs_MinDriver-Magnetization-09-0000169.omf
micromagneticdata/tests/test_sample/hysteresis/drive-0/hysteresis-Oxs_MinDriver-Magnetization-10-0000191.omf
micromagneticdata/tests/test_sample/hysteresis/drive-0/hysteresis-Oxs_MinDriver-Magnetization-11-0000216.omf
micromagneticdata/tests/test_sample/hysteresis/drive-0/hysteresis-Oxs_MinDriver-Magnetization-12-0000245.omf
micromagneticdata/tests/test_sample/hysteresis/drive-0/hysteresis-Oxs_MinDriver-Magnetization-13-0000818.omf
micromagneticdata-0.66.0.dist-info/licenses/LICENSE
micromagneticdata-0.66.0.dist-info/METADATA
micromagneticdata-0.66.0.dist-info/WHEEL
micromagneticdata-0.66.0.dist-info/top_level.txt
micromagneticdata-0.66.0.dist-info/RECORD
